{
    "$schema": "https://schema.management.azure.com/schemas/2015-01-01/deploymentParameters.json#",
    "contentVersion": "1.0.0.0",
    "parameters": {
        "functionAppName": {
            "value": ""
        },
        "location": {
            "value": ""
        },
        "functionAppClientId": {
            "value": ""
        },
        "keyVaultName": {
            "value": ""
        },
        "storageAccountName": {
            "value": ""
        },
        "applicationInsightsName": {
            "value": ""
        },
        "configStoreName": {
            "value": ""
        },
        "servicePrincipalObjectId": {
            "value": ""
        },
        "acrName": {
            "value": ""
        },
        "linuxFxVersion": {
            "value": ""
        },
        "dockerRegistryStartupCommand": {
            "value": ""
        },
        "hostingEnvironment": {
            "value": ""
        },
        "functionAppSku": {
            "value": "Basic"
        },
        "functionAppSkuCode": {
            "value": "B1"
        },
        "workerSize": {
            "value": "0"
        },
        "workerSizeId": {
            "value": "0"
        },
        "numberOfWorkers": {
            "value": "1"
        }
    }
}